synapse_auto_accept_invite/__init__.py
synapse_auto_accept_invite-1.2.0.dist-info/LICENSE
synapse_auto_accept_invite-1.2.0.dist-info/METADATA
synapse_auto_accept_invite-1.2.0.dist-info/WHEEL
synapse_auto_accept_invite-1.2.0.dist-info/top_level.txt
synapse_auto_accept_invite-1.2.0.dist-info/RECORD
