Metadata-Version: 2.1
Name: synapse_auto_accept_invite
Version: 1.2.0
Summary: "Synapse module to automatically accept invites"
Classifier: Development Status :: 5 - Production/Stable
Classifier: License :: OSI Approved :: Apache Software License
Classifier: Programming Language :: Python :: 3 :: Only
Requires-Python: >=3.7
License-File: LICENSE
Provides-Extra: dev
Requires-Dist: matrix-synapse >=1.84.0 ; extra == 'dev'
Requires-Dist: tox ; extra == 'dev'
Requires-Dist: twisted ; extra == 'dev'
Requires-Dist: aiounittest ; extra == 'dev'
Requires-Dist: attrs ; extra == 'dev'
Requires-Dist: frozendict ; extra == 'dev'
Requires-Dist: mypy ==1.4.1 ; extra == 'dev'
Requires-Dist: types-frozendict ; extra == 'dev'
Requires-Dist: black ==22.3.0 ; extra == 'dev'
Requires-Dist: flake8 ==5.0.4 ; extra == 'dev'
Requires-Dist: isort ==5.9.3 ; extra == 'dev'
